.DS_Store
deepkit/__init__.py
deepkit/client.py
deepkit/debugger.py
deepkit/deepkit_keras.py
deepkit/experiment.py
deepkit/globals.py
deepkit/home.py
deepkit/keras_tf.py
deepkit/model.py
deepkit/pytorch.py
deepkit/pytorch_graph.py
deepkit/utils/__init__.py
deepkit/utils/image.py
deepkit/utils/pilutil.py
deepkit-1.0.9.dist-info/METADATA
deepkit-1.0.9.dist-info/WHEEL
deepkit-1.0.9.dist-info/top_level.txt
deepkit-1.0.9.dist-info/RECORD
